squeakyv/__init__.py
squeakyv/_operations.py
squeakyv/core.py
squeakyv-0.1.1.dist-info/LICENSE
squeakyv-0.1.1.dist-info/METADATA
squeakyv-0.1.1.dist-info/WHEEL
squeakyv-0.1.1.dist-info/top_level.txt
squeakyv-0.1.1.dist-info/RECORD
