Metadata-Version: 2.2
Name: squeakyv
Version: 0.1.1
Summary: Simple SQLite-backed key-value caching library
Author: squeakyv contributors
License: MIT
Project-URL: Homepage, https://github.com/whacked/squeakyv
Project-URL: Repository, https://github.com/whacked/squeakyv
Project-URL: Issues, https://github.com/whacked/squeakyv/issues
Keywords: cache,sqlite,key-value,storage,memoization
Classifier: Development Status :: 3 - Alpha
Classifier: Intended Audience :: Developers
Classifier: License :: OSI Approved :: MIT License
Classifier: Programming Language :: Python :: 3
Classifier: Programming Language :: Python :: 3.9
Classifier: Programming Language :: Python :: 3.10
Classifier: Programming Language :: Python :: 3.11
Classifier: Programming Language :: Python :: 3.12
Classifier: Programming Language :: Python :: 3.13
Classifier: Topic :: Database
Classifier: Topic :: Software Development :: Libraries :: Python Modules
Classifier: Typing :: Typed
Requires-Python: >=3.9
License-File: LICENSE
